yolov9/__init__.py
yolov9/benchmarks.py
yolov9/detect.py
yolov9/export.py
yolov9/helpers.py
yolov9/train.py
yolov9/train_dual.py
yolov9/train_triple.py
yolov9/val.py
yolov9/val_dual.py
yolov9/val_triple.py
yolov9/models/__init__.py
yolov9/models/common.py
yolov9/models/experimental.py
yolov9/models/tf.py
yolov9/models/yolo.py
yolov9/utils/__init__.py
yolov9/utils/activations.py
yolov9/utils/augmentations.py
yolov9/utils/autoanchor.py
yolov9/utils/autobatch.py
yolov9/utils/callbacks.py
yolov9/utils/dataloaders.py
yolov9/utils/downloads.py
yolov9/utils/general.py
yolov9/utils/lion.py
yolov9/utils/loss.py
yolov9/utils/loss_tal.py
yolov9/utils/loss_tal_dual.py
yolov9/utils/loss_tal_triple.py
yolov9/utils/metrics.py
yolov9/utils/plots.py
yolov9/utils/torch_utils.py
yolov9/utils/triton.py
yolov9/utils/loggers/__init__.py
yolov9/utils/loggers/clearml/__init__.py
yolov9/utils/loggers/clearml/clearml_utils.py
yolov9/utils/loggers/clearml/hpo.py
yolov9/utils/loggers/comet/__init__.py
yolov9/utils/loggers/comet/comet_utils.py
yolov9/utils/loggers/comet/hpo.py
yolov9/utils/loggers/wandb/__init__.py
yolov9/utils/loggers/wandb/log_dataset.py
yolov9/utils/loggers/wandb/sweep.py
yolov9/utils/loggers/wandb/wandb_utils.py
yolov9/utils/panoptic/__init__.py
yolov9/utils/panoptic/augmentations.py
yolov9/utils/panoptic/dataloaders.py
yolov9/utils/panoptic/general.py
yolov9/utils/panoptic/loss.py
yolov9/utils/panoptic/loss_tal.py
yolov9/utils/panoptic/metrics.py
yolov9/utils/panoptic/plots.py
yolov9/utils/panoptic/tal/__init__.py
yolov9/utils/panoptic/tal/anchor_generator.py
yolov9/utils/panoptic/tal/assigner.py
yolov9/utils/segment/__init__.py
yolov9/utils/segment/augmentations.py
yolov9/utils/segment/dataloaders.py
yolov9/utils/segment/general.py
yolov9/utils/segment/loss.py
yolov9/utils/segment/loss_tal.py
yolov9/utils/segment/loss_tal_dual.py
yolov9/utils/segment/metrics.py
yolov9/utils/segment/plots.py
yolov9/utils/segment/tal/__init__.py
yolov9/utils/segment/tal/anchor_generator.py
yolov9_jm-1.0.0.dist-info/LICENSE
yolov9_jm-1.0.0.dist-info/METADATA
yolov9_jm-1.0.0.dist-info/WHEEL
yolov9_jm-1.0.0.dist-info/top_level.txt
yolov9_jm-1.0.0.dist-info/RECORD
