Metadata-Version: 2.1
Name: yolov9-jm
Version: 1.0.0
Summary: yolov9-jm
Home-page: https://github.com/najaemin92
Author: jaemin.na
Author-email: fixbi46@gmail.com
License: Apache License 2.0
Requires-Python: >=3.8
License-File: LICENSE
Requires-Dist: gitpython
Requires-Dist: ipython
Requires-Dist: matplotlib >=3.2.2
Requires-Dist: numpy >=1.18.5
Requires-Dist: opencv-python >=4.1.1
Requires-Dist: Pillow >=7.1.2
Requires-Dist: psutil
Requires-Dist: PyYAML >=5.3.1
Requires-Dist: requests >=2.23.0
Requires-Dist: scipy >=1.4.1
Requires-Dist: thop >=0.1.1
Requires-Dist: torch >=1.7.0
Requires-Dist: torchvision >=0.8.1
Requires-Dist: tqdm >=4.64.0
Requires-Dist: tensorboard >=2.4.1
Requires-Dist: pandas >=1.1.4
Requires-Dist: seaborn >=0.11.0
Requires-Dist: albumentations >=1.0.3
Requires-Dist: pycocotools >=2.0
